stencila/pyla/__init__.py
stencila/pyla/__main__.py
stencila/pyla/errors.py
stencila/pyla/interpreter.py
stencila/pyla/parser.py
stencila/pyla/servers.py
stencila/pyla/system.py
stencila_pyla-0.3.1.dist-info/METADATA
stencila_pyla-0.3.1.dist-info/WHEEL
stencila_pyla-0.3.1.dist-info/top_level.txt
stencila_pyla-0.3.1.dist-info/RECORD
