Metadata-Version: 2.1
Name: stencila-pyla
Version: 0.3.1
Summary: Python interpreter for executable documents
Home-page: https://github.com/stencila/pyla
Author: Stencila and contributors
Author-email: hello@stenci.la
License: Apache-2.0
Platform: UNKNOWN
Classifier: License :: OSI Approved :: Apache Software License
Classifier: Programming Language :: Python
Classifier: Programming Language :: Python :: 3
Classifier: Programming Language :: Python :: 3.7
Classifier: Programming Language :: Python :: Implementation :: CPython
Classifier: Programming Language :: Python :: Implementation :: PyPy
Requires-Python: >=3.7.0
Requires-Dist: astor (==0.8.1)
Requires-Dist: stencila-schema (==0.47.2)
